spw/__init__.py
spw/__main__.py
spw/main.py
spw-1.12.0.dist-info/LICENSE
spw-1.12.0.dist-info/METADATA
spw-1.12.0.dist-info/WHEEL
spw-1.12.0.dist-info/entry_points.txt
spw-1.12.0.dist-info/RECORD
