Metadata-Version: 2.1
Name: spw
Version: 1.12.0
Summary: store and retrieve passwords securely all while being scriptable!
Home-page: https://gitlab.com/drad/spw
License: GPL-3.0-only
Keywords: cli,encryption,password,openbox,scriptable
Author: drad
Author-email: sa@adercon.com
Maintainer: drad
Maintainer-email: sa@adercon.com
Requires-Python: >=3.11,<4.0
Classifier: License :: OSI Approved :: GNU General Public License v3 (GPLv3)
Classifier: Programming Language :: Python :: 3
Classifier: Programming Language :: Python :: 3.11
Classifier: Programming Language :: Python :: 3.12
Classifier: Programming Language :: Python :: 3.13
Requires-Dist: cryptography (>=43.0.3,<44.0.0)
Requires-Dist: lmdb (>=1.5.1,<2.0.0)
Project-URL: Repository, https://gitlab.com/drad/spw
